wordviz/__init__.py
wordviz/clustering.py
wordviz/dim_reduction.py
wordviz/encoding.py
wordviz/loading.py
wordviz/plotting.py
wordviz/plotting3d.py
wordviz/pretrained_embeddings.json
wordviz/similarity.py
wordviz/themes.json
wordviz-0.3.0.dist-info/LICENSE
wordviz-0.3.0.dist-info/METADATA
wordviz-0.3.0.dist-info/WHEEL
wordviz-0.3.0.dist-info/RECORD
