Metadata-Version: 2.3
Name: wordviz
Version: 0.3.0
Summary: A lightweight Python package for loading, analyzing, and visualizing word embeddings.
License: MIT
Author: Elena Zen
Author-email: elenazen563@gmail.com
Requires-Python: >=3.11,<3.13
Classifier: License :: OSI Approved :: MIT License
Classifier: Programming Language :: Python :: 3
Classifier: Programming Language :: Python :: 3.11
Classifier: Programming Language :: Python :: 3.12
Provides-Extra: encoding
Requires-Dist: adjusttext (>=1.3.0,<2.0.0)
Requires-Dist: gensim (>=4.3.3,<5.0.0)
Requires-Dist: ipykernel (>=6.29.5,<7.0.0)
Requires-Dist: jupyter (>=1.1.1,<2.0.0)
Requires-Dist: matplotlib (>=3.10.1,<4.0.0)
Requires-Dist: numpy (>=1.18.5,<2.4)
Requires-Dist: plotly (>=6.0.1,<7.0.0)
Requires-Dist: scikit-learn (>=1.6.1,<2.0.0)
Requires-Dist: scipy (>=1.7.0,<1.14.0)
Requires-Dist: seaborn (>=0.13.2,<0.14.0)
Requires-Dist: sentence-transformers (>=2.0.0) ; extra == "encoding"
Requires-Dist: torch (>=1.12.0) ; extra == "encoding"
Requires-Dist: transformers (>=4.20.0) ; extra == "encoding"
Requires-Dist: umap-learn (>=0.5.7,<0.6.0)
